jabagram/__init__.py
jabagram/database/base.py
jabagram/database/chats.py
jabagram/database/messages.py
jabagram/database/stickers.py
jabagram/database/topics.py
jabagram/dispatcher.py
jabagram/messages.py
jabagram/model.py
jabagram/runner.py
jabagram/service.py
jabagram/telegram/api.py
jabagram/telegram/client.py
jabagram/telegram/handler.py
jabagram/telegram/model.py
jabagram/xmpp/actor.py
jabagram/xmpp/client.py
jabagram/xmpp/handler.py
jabagram-1.1.0.dist-info/METADATA
jabagram-1.1.0.dist-info/WHEEL
jabagram-1.1.0.dist-info/entry_points.txt
jabagram-1.1.0.dist-info/licenses/LICENSE
jabagram-1.1.0.dist-info/RECORD
