Metadata-Version: 2.4
Name: jabagram
Version: 1.1.0
Summary: Fully functional bridge between Telegram and XMPP
License-Expression: GPL-3.0-only
License-File: LICENSE
Keywords: xmpp,telegram,asyncio,bridge
Author: Vasiliy Stelmachenok
Author-email: ventureo@yandex.ru
Maintainer: Vasiliy Stelmachenok
Maintainer-email: ventureo@yandex.ru
Requires-Python: >= 3.10
Classifier: Development Status :: 5 - Production/Stable
Classifier: Programming Language :: Python
Classifier: Programming Language :: Python :: 3.10
Classifier: Programming Language :: Python :: 3.11
Classifier: Programming Language :: Python :: 3.12
Requires-Dist: aiohttp
Requires-Dist: slixmpp
Requires-Dist: unidecode
Project-URL: Bug Tracker, https://github.com/ventureoo/jabagram/issues
Project-URL: Homepage, https://github.com/ventureoo/jabagram
Project-URL: Repository, https://github.com/ventureoo/jabagram.git
